{
  "collectionName": "components_form_fields",
  "info": {
    "displayName": "Form Fields",
    "icon": "bulletList",
    "description": ""
  },
  "options": {},
  "attributes": {
    "label": {
      "type": "string"
    },
    "fieldType": {
      "type": "enumeration",
      "enum": [
        "text",
        "number",
        "email",
        "textarea",
        "select",
        "upload",
        "date",
        "datetime",
        "time",
        "checkbox",
        "radio",
        "hidden",
        "phone",
        "rating",
        "multiselect"
      ],
      "required": true,
      "default": "text"
    },
    "required": {
      "type": "boolean",
      "default": false
    },
    "customErrorMessage": {
      "type": "string"
    },
    "submissionKey": {
      "type": "string"
    },
    "placeholder": {
      "type": "string"
    },
    "selectOptions": {
      "displayName": "Select Options",
      "type": "component",
      "repeatable": true,
      "component": "form.select-options"
    },
    "formOrder": {
      "pluginOptions": {
        "i18n": {
          "localized": false
        }
      },
      "type": "integer"
    },
    "maxFiles": {
      "type": "integer",
      "pluginOptions": {
        "i18n": {
          "localized": false
        }
      }
    }
  }
}
